<model>
<column loop="true"><itemfirst displayname="0" />
<itemfirst displayname="1" />
<itemfirst displayname="2" />
<itemfirst displayname="3" />
<itemfirst displayname="4" />
<itemfirst displayname="5" />
<itemfirst displayname="6" />
<itemfirst displayname="7" />
<itemfirst displayname="8" />
<itemfirst displayname="9" />
<itemfirst displayname="10" />
<itemfirst displayname="11" />
<itemfirst displayname="12" />
<itemfirst displayname="13" />
<itemfirst displayname="14" />
<itemfirst displayname="15" />
<itemfirst displayname="16" />
<itemfirst displayname="17" />
<itemfirst displayname="18" />
<itemfirst displayname="19" />
<itemfirst displayname="20" />
<itemfirst displayname="21" />
<itemfirst displayname="22" />
<itemfirst displayname="23" />
<itemfirst displayname="24" />
<itemfirst displayname="25" />
<itemfirst displayname="26" />
<itemfirst displayname="27" />
<itemfirst displayname="28" />
<itemfirst displayname="29" />
<itemfirst displayname="30" />
<itemfirst displayname="31" />
<itemfirst displayname="32" />
<itemfirst displayname="33" />
<itemfirst displayname="34" />
<itemfirst displayname="35" />
<itemfirst displayname="36" />
<itemfirst displayname="37" />
<itemfirst displayname="38" />
<itemfirst displayname="39" />
<itemfirst displayname="40" />
<itemfirst displayname="41" />
<itemfirst displayname="42" />
<itemfirst displayname="43" />
<itemfirst displayname="44" />
<itemfirst displayname="45" />
<itemfirst displayname="46" />
<itemfirst displayname="47" />
<itemfirst displayname="48" />
<itemfirst displayname="49" />
<itemfirst displayname="50" />
<itemfirst displayname="51" />
<itemfirst displayname="52" />
<itemfirst displayname="53" />
<itemfirst displayname="54" />
<itemfirst displayname="55" />
<itemfirst displayname="56" />
<itemfirst displayname="57" />
<itemfirst displayname="58" />
<itemfirst displayname="59" />
<itemfirst displayname="60" />
<itemfirst displayname="61" />
<itemfirst displayname="62" />
<itemfirst displayname="63" />
<itemfirst displayname="64" />
<itemfirst displayname="65" />
<itemfirst displayname="66" />
<itemfirst displayname="67" />
<itemfirst displayname="68" />
<itemfirst displayname="69" />
<itemfirst displayname="70" />
<itemfirst displayname="71" />
<itemfirst displayname="72" />
<itemfirst displayname="73" />
<itemfirst displayname="74" />
<itemfirst displayname="75" />
<itemfirst displayname="76" />
<itemfirst displayname="77" />
<itemfirst displayname="78" />
<itemfirst displayname="79" />
<itemfirst displayname="80" />
<itemfirst displayname="81" />
<itemfirst displayname="82" />
<itemfirst displayname="83" />
<itemfirst displayname="84" />
<itemfirst displayname="85" />
<itemfirst displayname="86" />
<itemfirst displayname="87" />
<itemfirst displayname="88" />
<itemfirst displayname="89" />
<itemfirst displayname="90" />
<itemfirst displayname="91" />
<itemfirst displayname="92" />
<itemfirst displayname="93" />
<itemfirst displayname="94" />
<itemfirst displayname="95" />
<itemfirst displayname="96" />
<itemfirst displayname="97" />
<itemfirst displayname="98" />
<itemfirst displayname="99" />
<itemfirst displayname="100" />
<itemfirst displayname="101" />
<itemfirst displayname="102" />
<itemfirst displayname="103" />
<itemfirst displayname="104" />
<itemfirst displayname="105" />
<itemfirst displayname="106" />
<itemfirst displayname="107" />
<itemfirst displayname="108" />
<itemfirst displayname="109" />
<itemfirst displayname="110" />
<itemfirst displayname="111" />
<itemfirst displayname="112" />
<itemfirst displayname="113" />
<itemfirst displayname="114" />
<itemfirst displayname="115" />
<itemfirst displayname="116" />
<itemfirst displayname="117" />
<itemfirst displayname="118" />
<itemfirst displayname="119" />
<itemfirst displayname="120" />
<itemfirst displayname="121" />
<itemfirst displayname="122" />
<itemfirst displayname="123" />
<itemfirst displayname="124" />
<itemfirst displayname="125" />
<itemfirst displayname="126" />
<itemfirst displayname="127" />
<itemfirst displayname="128" />
<itemfirst displayname="129" />
<itemfirst displayname="130" />
<itemfirst displayname="131" />
<itemfirst displayname="132" />
<itemfirst displayname="133" />
<itemfirst displayname="134" />
<itemfirst displayname="135" />
<itemfirst displayname="136" />
<itemfirst displayname="137" />
<itemfirst displayname="138" />
<itemfirst displayname="139" />
<itemfirst displayname="140" />
<itemfirst displayname="141" />
<itemfirst displayname="142" />
<itemfirst displayname="143" />
<itemfirst displayname="144" />
<itemfirst displayname="145" />
<itemfirst displayname="146" />
<itemfirst displayname="147" />
<itemfirst displayname="148" />
<itemfirst displayname="149" />
<itemfirst displayname="150" />
<itemfirst displayname="151" />
<itemfirst displayname="152" />
<itemfirst displayname="153" />
<itemfirst displayname="154" />
<itemfirst displayname="155" />
<itemfirst displayname="156" />
<itemfirst displayname="157" />
<itemfirst displayname="158" />
<itemfirst displayname="159" />
<itemfirst displayname="160" />
<itemfirst displayname="161" />
<itemfirst displayname="162" />
<itemfirst displayname="163" />
<itemfirst displayname="164" />
<itemfirst displayname="165" />
<itemfirst displayname="166" />
<itemfirst displayname="167" />
<itemfirst displayname="168" />
<itemfirst displayname="169" />
<itemfirst displayname="170" />
<itemfirst displayname="171" />
<itemfirst displayname="172" />
<itemfirst displayname="173" />
<itemfirst displayname="174" />
<itemfirst displayname="175" />
<itemfirst displayname="176" />
<itemfirst displayname="177" />
<itemfirst displayname="178" />
<itemfirst displayname="179" />
<itemfirst displayname="180" />
<itemfirst displayname="181" />
<itemfirst displayname="182" />
<itemfirst displayname="183" />
<itemfirst displayname="184" />
<itemfirst displayname="185" />
<itemfirst displayname="186" />
<itemfirst displayname="187" />
<itemfirst displayname="188" />
<itemfirst displayname="189" />
<itemfirst displayname="190" />
<itemfirst displayname="191" />
<itemfirst displayname="192" />
<itemfirst displayname="193" />
<itemfirst displayname="194" />
<itemfirst displayname="195" />
<itemfirst displayname="196" />
<itemfirst displayname="197" />
<itemfirst displayname="198" />
<itemfirst displayname="199" />
<itemfirst displayname="200" />
<itemfirst displayname="201" />
<itemfirst displayname="202" />
<itemfirst displayname="203" />
<itemfirst displayname="204" />
<itemfirst displayname="205" />
<itemfirst displayname="206" />
<itemfirst displayname="207" />
<itemfirst displayname="208" />
<itemfirst displayname="209" />
<itemfirst displayname="210" />
<itemfirst displayname="211" />
<itemfirst displayname="212" />
<itemfirst displayname="213" />
<itemfirst displayname="214" />
<itemfirst displayname="215" />
<itemfirst displayname="216" />
<itemfirst displayname="217" />
<itemfirst displayname="218" />
<itemfirst displayname="219" />
<itemfirst displayname="220" />
<itemfirst displayname="221" />
<itemfirst displayname="222" />
<itemfirst displayname="223" />
<itemfirst displayname="224" />
<itemfirst displayname="225" />
<itemfirst displayname="226" />
<itemfirst displayname="227" />
<itemfirst displayname="228" />
<itemfirst displayname="229" />
<itemfirst displayname="230" />
<itemfirst displayname="231" />
<itemfirst displayname="232" />
<itemfirst displayname="233" />
<itemfirst displayname="234" />
<itemfirst displayname="235" />
<itemfirst displayname="236" />
<itemfirst displayname="237" />
<itemfirst displayname="238" />
<itemfirst displayname="239" />
<itemfirst displayname="240" />
<itemfirst displayname="241" />
<itemfirst displayname="242" />
<itemfirst displayname="243" />
<itemfirst displayname="244" />
<itemfirst displayname="245" />
<itemfirst displayname="246" />
<itemfirst displayname="247" />
<itemfirst displayname="248" />
<itemfirst displayname="249" />
<itemfirst displayname="250" />
<itemfirst displayname="251" />
<itemfirst displayname="252" />
<itemfirst displayname="253" />
<itemfirst displayname="254" />
</column>
<column loop="true"><itemsecond displayname="0" />
<itemsecond displayname="1" />
<itemsecond displayname="2" />
<itemsecond displayname="3" />
<itemsecond displayname="4" />
<itemsecond displayname="5" />
<itemsecond displayname="6" />
<itemsecond displayname="7" />
<itemsecond displayname="8" />
<itemsecond displayname="9" />
<itemsecond displayname="10" />
<itemsecond displayname="11" />
<itemsecond displayname="12" />
<itemsecond displayname="13" />
<itemsecond displayname="14" />
<itemsecond displayname="15" />
<itemsecond displayname="16" />
<itemsecond displayname="17" />
<itemsecond displayname="18" />
<itemsecond displayname="19" />
<itemsecond displayname="20" />
<itemsecond displayname="21" />
<itemsecond displayname="22" />
<itemsecond displayname="23" />
<itemsecond displayname="24" />
<itemsecond displayname="25" />
<itemsecond displayname="26" />
<itemsecond displayname="27" />
<itemsecond displayname="28" />
<itemsecond displayname="29" />
<itemsecond displayname="30" />
<itemsecond displayname="31" />
<itemsecond displayname="32" />
<itemsecond displayname="33" />
<itemsecond displayname="34" />
<itemsecond displayname="35" />
<itemsecond displayname="36" />
<itemsecond displayname="37" />
<itemsecond displayname="38" />
<itemsecond displayname="39" />
<itemsecond displayname="40" />
<itemsecond displayname="41" />
<itemsecond displayname="42" />
<itemsecond displayname="43" />
<itemsecond displayname="44" />
<itemsecond displayname="45" />
<itemsecond displayname="46" />
<itemsecond displayname="47" />
<itemsecond displayname="48" />
<itemsecond displayname="49" />
<itemsecond displayname="50" />
<itemsecond displayname="51" />
<itemsecond displayname="52" />
<itemsecond displayname="53" />
<itemsecond displayname="54" />
<itemsecond displayname="55" />
<itemsecond displayname="56" />
<itemsecond displayname="57" />
<itemsecond displayname="58" />
<itemsecond displayname="59" />
<itemsecond displayname="60" />
<itemsecond displayname="61" />
<itemsecond displayname="62" />
<itemsecond displayname="63" />
<itemsecond displayname="64" />
<itemsecond displayname="65" />
<itemsecond displayname="66" />
<itemsecond displayname="67" />
<itemsecond displayname="68" />
<itemsecond displayname="69" />
<itemsecond displayname="70" />
<itemsecond displayname="71" />
<itemsecond displayname="72" />
<itemsecond displayname="73" />
<itemsecond displayname="74" />
<itemsecond displayname="75" />
<itemsecond displayname="76" />
<itemsecond displayname="77" />
<itemsecond displayname="78" />
<itemsecond displayname="79" />
<itemsecond displayname="80" />
<itemsecond displayname="81" />
<itemsecond displayname="82" />
<itemsecond displayname="83" />
<itemsecond displayname="84" />
<itemsecond displayname="85" />
<itemsecond displayname="86" />
<itemsecond displayname="87" />
<itemsecond displayname="88" />
<itemsecond displayname="89" />
<itemsecond displayname="90" />
<itemsecond displayname="91" />
<itemsecond displayname="92" />
<itemsecond displayname="93" />
<itemsecond displayname="94" />
<itemsecond displayname="95" />
<itemsecond displayname="96" />
<itemsecond displayname="97" />
<itemsecond displayname="98" />
<itemsecond displayname="99" />
<itemsecond displayname="100" />
<itemsecond displayname="101" />
<itemsecond displayname="102" />
<itemsecond displayname="103" />
<itemsecond displayname="104" />
<itemsecond displayname="105" />
<itemsecond displayname="106" />
<itemsecond displayname="107" />
<itemsecond displayname="108" />
<itemsecond displayname="109" />
<itemsecond displayname="110" />
<itemsecond displayname="111" />
<itemsecond displayname="112" />
<itemsecond displayname="113" />
<itemsecond displayname="114" />
<itemsecond displayname="115" />
<itemsecond displayname="116" />
<itemsecond displayname="117" />
<itemsecond displayname="118" />
<itemsecond displayname="119" />
<itemsecond displayname="120" />
<itemsecond displayname="121" />
<itemsecond displayname="122" />
<itemsecond displayname="123" />
<itemsecond displayname="124" />
<itemsecond displayname="125" />
<itemsecond displayname="126" />
<itemsecond displayname="127" />
<itemsecond displayname="128" />
<itemsecond displayname="129" />
<itemsecond displayname="130" />
<itemsecond displayname="131" />
<itemsecond displayname="132" />
<itemsecond displayname="133" />
<itemsecond displayname="134" />
<itemsecond displayname="135" />
<itemsecond displayname="136" />
<itemsecond displayname="137" />
<itemsecond displayname="138" />
<itemsecond displayname="139" />
<itemsecond displayname="140" />
<itemsecond displayname="141" />
<itemsecond displayname="142" />
<itemsecond displayname="143" />
<itemsecond displayname="144" />
<itemsecond displayname="145" />
<itemsecond displayname="146" />
<itemsecond displayname="147" />
<itemsecond displayname="148" />
<itemsecond displayname="149" />
<itemsecond displayname="150" />
<itemsecond displayname="151" />
<itemsecond displayname="152" />
<itemsecond displayname="153" />
<itemsecond displayname="154" />
<itemsecond displayname="155" />
<itemsecond displayname="156" />
<itemsecond displayname="157" />
<itemsecond displayname="158" />
<itemsecond displayname="159" />
<itemsecond displayname="160" />
<itemsecond displayname="161" />
<itemsecond displayname="162" />
<itemsecond displayname="163" />
<itemsecond displayname="164" />
<itemsecond displayname="165" />
<itemsecond displayname="166" />
<itemsecond displayname="167" />
<itemsecond displayname="168" />
<itemsecond displayname="169" />
<itemsecond displayname="170" />
<itemsecond displayname="171" />
<itemsecond displayname="172" />
<itemsecond displayname="173" />
<itemsecond displayname="174" />
<itemsecond displayname="175" />
<itemsecond displayname="176" />
<itemsecond displayname="177" />
<itemsecond displayname="178" />
<itemsecond displayname="179" />
<itemsecond displayname="180" />
<itemsecond displayname="181" />
<itemsecond displayname="182" />
<itemsecond displayname="183" />
<itemsecond displayname="184" />
<itemsecond displayname="185" />
<itemsecond displayname="186" />
<itemsecond displayname="187" />
<itemsecond displayname="188" />
<itemsecond displayname="189" />
<itemsecond displayname="190" />
<itemsecond displayname="191" />
<itemsecond displayname="192" />
<itemsecond displayname="193" />
<itemsecond displayname="194" />
<itemsecond displayname="195" />
<itemsecond displayname="196" />
<itemsecond displayname="197" />
<itemsecond displayname="198" />
<itemsecond displayname="199" />
<itemsecond displayname="200" />
<itemsecond displayname="201" />
<itemsecond displayname="202" />
<itemsecond displayname="203" />
<itemsecond displayname="204" />
<itemsecond displayname="205" />
<itemsecond displayname="206" />
<itemsecond displayname="207" />
<itemsecond displayname="208" />
<itemsecond displayname="209" />
<itemsecond displayname="210" />
<itemsecond displayname="211" />
<itemsecond displayname="212" />
<itemsecond displayname="213" />
<itemsecond displayname="214" />
<itemsecond displayname="215" />
<itemsecond displayname="216" />
<itemsecond displayname="217" />
<itemsecond displayname="218" />
<itemsecond displayname="219" />
<itemsecond displayname="220" />
<itemsecond displayname="221" />
<itemsecond displayname="222" />
<itemsecond displayname="223" />
<itemsecond displayname="224" />
<itemsecond displayname="225" />
<itemsecond displayname="226" />
<itemsecond displayname="227" />
<itemsecond displayname="228" />
<itemsecond displayname="229" />
<itemsecond displayname="230" />
<itemsecond displayname="231" />
<itemsecond displayname="232" />
<itemsecond displayname="233" />
<itemsecond displayname="234" />
<itemsecond displayname="235" />
<itemsecond displayname="236" />
<itemsecond displayname="237" />
<itemsecond displayname="238" />
<itemsecond displayname="239" />
<itemsecond displayname="240" />
<itemsecond displayname="241" />
<itemsecond displayname="242" />
<itemsecond displayname="243" />
<itemsecond displayname="244" />
<itemsecond displayname="245" />
<itemsecond displayname="246" />
<itemsecond displayname="247" />
<itemsecond displayname="248" />
<itemsecond displayname="249" />
<itemsecond displayname="250" />
<itemsecond displayname="251" />
<itemsecond displayname="252" />
<itemsecond displayname="253" />
<itemsecond displayname="254" />
</column>
<column loop="true"><itemthird displayname="0" />
<itemthird displayname="1" />
<itemthird displayname="2" />
<itemthird displayname="3" />
<itemthird displayname="4" />
<itemthird displayname="5" />
<itemthird displayname="6" />
<itemthird displayname="7" />
<itemthird displayname="8" />
<itemthird displayname="9" />
<itemthird displayname="10" />
<itemthird displayname="11" />
<itemthird displayname="12" />
<itemthird displayname="13" />
<itemthird displayname="14" />
<itemthird displayname="15" />
<itemthird displayname="16" />
<itemthird displayname="17" />
<itemthird displayname="18" />
<itemthird displayname="19" />
<itemthird displayname="20" />
<itemthird displayname="21" />
<itemthird displayname="22" />
<itemthird displayname="23" />
<itemthird displayname="24" />
<itemthird displayname="25" />
<itemthird displayname="26" />
<itemthird displayname="27" />
<itemthird displayname="28" />
<itemthird displayname="29" />
<itemthird displayname="30" />
<itemthird displayname="31" />
<itemthird displayname="32" />
<itemthird displayname="33" />
<itemthird displayname="34" />
<itemthird displayname="35" />
<itemthird displayname="36" />
<itemthird displayname="37" />
<itemthird displayname="38" />
<itemthird displayname="39" />
<itemthird displayname="40" />
<itemthird displayname="41" />
<itemthird displayname="42" />
<itemthird displayname="43" />
<itemthird displayname="44" />
<itemthird displayname="45" />
<itemthird displayname="46" />
<itemthird displayname="47" />
<itemthird displayname="48" />
<itemthird displayname="49" />
<itemthird displayname="50" />
<itemthird displayname="51" />
<itemthird displayname="52" />
<itemthird displayname="53" />
<itemthird displayname="54" />
<itemthird displayname="55" />
<itemthird displayname="56" />
<itemthird displayname="57" />
<itemthird displayname="58" />
<itemthird displayname="59" />
<itemthird displayname="60" />
<itemthird displayname="61" />
<itemthird displayname="62" />
<itemthird displayname="63" />
<itemthird displayname="64" />
<itemthird displayname="65" />
<itemthird displayname="66" />
<itemthird displayname="67" />
<itemthird displayname="68" />
<itemthird displayname="69" />
<itemthird displayname="70" />
<itemthird displayname="71" />
<itemthird displayname="72" />
<itemthird displayname="73" />
<itemthird displayname="74" />
<itemthird displayname="75" />
<itemthird displayname="76" />
<itemthird displayname="77" />
<itemthird displayname="78" />
<itemthird displayname="79" />
<itemthird displayname="80" />
<itemthird displayname="81" />
<itemthird displayname="82" />
<itemthird displayname="83" />
<itemthird displayname="84" />
<itemthird displayname="85" />
<itemthird displayname="86" />
<itemthird displayname="87" />
<itemthird displayname="88" />
<itemthird displayname="89" />
<itemthird displayname="90" />
<itemthird displayname="91" />
<itemthird displayname="92" />
<itemthird displayname="93" />
<itemthird displayname="94" />
<itemthird displayname="95" />
<itemthird displayname="96" />
<itemthird displayname="97" />
<itemthird displayname="98" />
<itemthird displayname="99" />
<itemthird displayname="100" />
<itemthird displayname="101" />
<itemthird displayname="102" />
<itemthird displayname="103" />
<itemthird displayname="104" />
<itemthird displayname="105" />
<itemthird displayname="106" />
<itemthird displayname="107" />
<itemthird displayname="108" />
<itemthird displayname="109" />
<itemthird displayname="110" />
<itemthird displayname="111" />
<itemthird displayname="112" />
<itemthird displayname="113" />
<itemthird displayname="114" />
<itemthird displayname="115" />
<itemthird displayname="116" />
<itemthird displayname="117" />
<itemthird displayname="118" />
<itemthird displayname="119" />
<itemthird displayname="120" />
<itemthird displayname="121" />
<itemthird displayname="122" />
<itemthird displayname="123" />
<itemthird displayname="124" />
<itemthird displayname="125" />
<itemthird displayname="126" />
<itemthird displayname="127" />
<itemthird displayname="128" />
<itemthird displayname="129" />
<itemthird displayname="130" />
<itemthird displayname="131" />
<itemthird displayname="132" />
<itemthird displayname="133" />
<itemthird displayname="134" />
<itemthird displayname="135" />
<itemthird displayname="136" />
<itemthird displayname="137" />
<itemthird displayname="138" />
<itemthird displayname="139" />
<itemthird displayname="140" />
<itemthird displayname="141" />
<itemthird displayname="142" />
<itemthird displayname="143" />
<itemthird displayname="144" />
<itemthird displayname="145" />
<itemthird displayname="146" />
<itemthird displayname="147" />
<itemthird displayname="148" />
<itemthird displayname="149" />
<itemthird displayname="150" />
<itemthird displayname="151" />
<itemthird displayname="152" />
<itemthird displayname="153" />
<itemthird displayname="154" />
<itemthird displayname="155" />
<itemthird displayname="156" />
<itemthird displayname="157" />
<itemthird displayname="158" />
<itemthird displayname="159" />
<itemthird displayname="160" />
<itemthird displayname="161" />
<itemthird displayname="162" />
<itemthird displayname="163" />
<itemthird displayname="164" />
<itemthird displayname="165" />
<itemthird displayname="166" />
<itemthird displayname="167" />
<itemthird displayname="168" />
<itemthird displayname="169" />
<itemthird displayname="170" />
<itemthird displayname="171" />
<itemthird displayname="172" />
<itemthird displayname="173" />
<itemthird displayname="174" />
<itemthird displayname="175" />
<itemthird displayname="176" />
<itemthird displayname="177" />
<itemthird displayname="178" />
<itemthird displayname="179" />
<itemthird displayname="180" />
<itemthird displayname="181" />
<itemthird displayname="182" />
<itemthird displayname="183" />
<itemthird displayname="184" />
<itemthird displayname="185" />
<itemthird displayname="186" />
<itemthird displayname="187" />
<itemthird displayname="188" />
<itemthird displayname="189" />
<itemthird displayname="190" />
<itemthird displayname="191" />
<itemthird displayname="192" />
<itemthird displayname="193" />
<itemthird displayname="194" />
<itemthird displayname="195" />
<itemthird displayname="196" />
<itemthird displayname="197" />
<itemthird displayname="198" />
<itemthird displayname="199" />
<itemthird displayname="200" />
<itemthird displayname="201" />
<itemthird displayname="202" />
<itemthird displayname="203" />
<itemthird displayname="204" />
<itemthird displayname="205" />
<itemthird displayname="206" />
<itemthird displayname="207" />
<itemthird displayname="208" />
<itemthird displayname="209" />
<itemthird displayname="210" />
<itemthird displayname="211" />
<itemthird displayname="212" />
<itemthird displayname="213" />
<itemthird displayname="214" />
<itemthird displayname="215" />
<itemthird displayname="216" />
<itemthird displayname="217" />
<itemthird displayname="218" />
<itemthird displayname="219" />
<itemthird displayname="220" />
<itemthird displayname="221" />
<itemthird displayname="222" />
<itemthird displayname="223" />
<itemthird displayname="224" />
<itemthird displayname="225" />
<itemthird displayname="226" />
<itemthird displayname="227" />
<itemthird displayname="228" />
<itemthird displayname="229" />
<itemthird displayname="230" />
<itemthird displayname="231" />
<itemthird displayname="232" />
<itemthird displayname="233" />
<itemthird displayname="234" />
<itemthird displayname="235" />
<itemthird displayname="236" />
<itemthird displayname="237" />
<itemthird displayname="238" />
<itemthird displayname="239" />
<itemthird displayname="240" />
<itemthird displayname="241" />
<itemthird displayname="242" />
<itemthird displayname="243" />
<itemthird displayname="244" />
<itemthird displayname="245" />
<itemthird displayname="246" />
<itemthird displayname="247" />
<itemthird displayname="248" />
<itemthird displayname="249" />
<itemthird displayname="250" />
<itemthird displayname="251" />
<itemthird displayname="252" />
<itemthird displayname="253" />
<itemthird displayname="254" />
</column>
<column loop="true"><itemfourth displayname="0" />
<itemfourth displayname="1" />
<itemfourth displayname="2" />
<itemfourth displayname="3" />
<itemfourth displayname="4" />
<itemfourth displayname="5" />
<itemfourth displayname="6" />
<itemfourth displayname="7" />
<itemfourth displayname="8" />
<itemfourth displayname="9" />
<itemfourth displayname="10" />
<itemfourth displayname="11" />
<itemfourth displayname="12" />
<itemfourth displayname="13" />
<itemfourth displayname="14" />
<itemfourth displayname="15" />
<itemfourth displayname="16" />
<itemfourth displayname="17" />
<itemfourth displayname="18" />
<itemfourth displayname="19" />
<itemfourth displayname="20" />
<itemfourth displayname="21" />
<itemfourth displayname="22" />
<itemfourth displayname="23" />
<itemfourth displayname="24" />
<itemfourth displayname="25" />
<itemfourth displayname="26" />
<itemfourth displayname="27" />
<itemfourth displayname="28" />
<itemfourth displayname="29" />
<itemfourth displayname="30" />
<itemfourth displayname="31" />
<itemfourth displayname="32" />
<itemfourth displayname="33" />
<itemfourth displayname="34" />
<itemfourth displayname="35" />
<itemfourth displayname="36" />
<itemfourth displayname="37" />
<itemfourth displayname="38" />
<itemfourth displayname="39" />
<itemfourth displayname="40" />
<itemfourth displayname="41" />
<itemfourth displayname="42" />
<itemfourth displayname="43" />
<itemfourth displayname="44" />
<itemfourth displayname="45" />
<itemfourth displayname="46" />
<itemfourth displayname="47" />
<itemfourth displayname="48" />
<itemfourth displayname="49" />
<itemfourth displayname="50" />
<itemfourth displayname="51" />
<itemfourth displayname="52" />
<itemfourth displayname="53" />
<itemfourth displayname="54" />
<itemfourth displayname="55" />
<itemfourth displayname="56" />
<itemfourth displayname="57" />
<itemfourth displayname="58" />
<itemfourth displayname="59" />
<itemfourth displayname="60" />
<itemfourth displayname="61" />
<itemfourth displayname="62" />
<itemfourth displayname="63" />
<itemfourth displayname="64" />
<itemfourth displayname="65" />
<itemfourth displayname="66" />
<itemfourth displayname="67" />
<itemfourth displayname="68" />
<itemfourth displayname="69" />
<itemfourth displayname="70" />
<itemfourth displayname="71" />
<itemfourth displayname="72" />
<itemfourth displayname="73" />
<itemfourth displayname="74" />
<itemfourth displayname="75" />
<itemfourth displayname="76" />
<itemfourth displayname="77" />
<itemfourth displayname="78" />
<itemfourth displayname="79" />
<itemfourth displayname="80" />
<itemfourth displayname="81" />
<itemfourth displayname="82" />
<itemfourth displayname="83" />
<itemfourth displayname="84" />
<itemfourth displayname="85" />
<itemfourth displayname="86" />
<itemfourth displayname="87" />
<itemfourth displayname="88" />
<itemfourth displayname="89" />
<itemfourth displayname="90" />
<itemfourth displayname="91" />
<itemfourth displayname="92" />
<itemfourth displayname="93" />
<itemfourth displayname="94" />
<itemfourth displayname="95" />
<itemfourth displayname="96" />
<itemfourth displayname="97" />
<itemfourth displayname="98" />
<itemfourth displayname="99" />
<itemfourth displayname="100" />
<itemfourth displayname="101" />
<itemfourth displayname="102" />
<itemfourth displayname="103" />
<itemfourth displayname="104" />
<itemfourth displayname="105" />
<itemfourth displayname="106" />
<itemfourth displayname="107" />
<itemfourth displayname="108" />
<itemfourth displayname="109" />
<itemfourth displayname="110" />
<itemfourth displayname="111" />
<itemfourth displayname="112" />
<itemfourth displayname="113" />
<itemfourth displayname="114" />
<itemfourth displayname="115" />
<itemfourth displayname="116" />
<itemfourth displayname="117" />
<itemfourth displayname="118" />
<itemfourth displayname="119" />
<itemfourth displayname="120" />
<itemfourth displayname="121" />
<itemfourth displayname="122" />
<itemfourth displayname="123" />
<itemfourth displayname="124" />
<itemfourth displayname="125" />
<itemfourth displayname="126" />
<itemfourth displayname="127" />
<itemfourth displayname="128" />
<itemfourth displayname="129" />
<itemfourth displayname="130" />
<itemfourth displayname="131" />
<itemfourth displayname="132" />
<itemfourth displayname="133" />
<itemfourth displayname="134" />
<itemfourth displayname="135" />
<itemfourth displayname="136" />
<itemfourth displayname="137" />
<itemfourth displayname="138" />
<itemfourth displayname="139" />
<itemfourth displayname="140" />
<itemfourth displayname="141" />
<itemfourth displayname="142" />
<itemfourth displayname="143" />
<itemfourth displayname="144" />
<itemfourth displayname="145" />
<itemfourth displayname="146" />
<itemfourth displayname="147" />
<itemfourth displayname="148" />
<itemfourth displayname="149" />
<itemfourth displayname="150" />
<itemfourth displayname="151" />
<itemfourth displayname="152" />
<itemfourth displayname="153" />
<itemfourth displayname="154" />
<itemfourth displayname="155" />
<itemfourth displayname="156" />
<itemfourth displayname="157" />
<itemfourth displayname="158" />
<itemfourth displayname="159" />
<itemfourth displayname="160" />
<itemfourth displayname="161" />
<itemfourth displayname="162" />
<itemfourth displayname="163" />
<itemfourth displayname="164" />
<itemfourth displayname="165" />
<itemfourth displayname="166" />
<itemfourth displayname="167" />
<itemfourth displayname="168" />
<itemfourth displayname="169" />
<itemfourth displayname="170" />
<itemfourth displayname="171" />
<itemfourth displayname="172" />
<itemfourth displayname="173" />
<itemfourth displayname="174" />
<itemfourth displayname="175" />
<itemfourth displayname="176" />
<itemfourth displayname="177" />
<itemfourth displayname="178" />
<itemfourth displayname="179" />
<itemfourth displayname="180" />
<itemfourth displayname="181" />
<itemfourth displayname="182" />
<itemfourth displayname="183" />
<itemfourth displayname="184" />
<itemfourth displayname="185" />
<itemfourth displayname="186" />
<itemfourth displayname="187" />
<itemfourth displayname="188" />
<itemfourth displayname="189" />
<itemfourth displayname="190" />
<itemfourth displayname="191" />
<itemfourth displayname="192" />
<itemfourth displayname="193" />
<itemfourth displayname="194" />
<itemfourth displayname="195" />
<itemfourth displayname="196" />
<itemfourth displayname="197" />
<itemfourth displayname="198" />
<itemfourth displayname="199" />
<itemfourth displayname="200" />
<itemfourth displayname="201" />
<itemfourth displayname="202" />
<itemfourth displayname="203" />
<itemfourth displayname="204" />
<itemfourth displayname="205" />
<itemfourth displayname="206" />
<itemfourth displayname="207" />
<itemfourth displayname="208" />
<itemfourth displayname="209" />
<itemfourth displayname="210" />
<itemfourth displayname="211" />
<itemfourth displayname="212" />
<itemfourth displayname="213" />
<itemfourth displayname="214" />
<itemfourth displayname="215" />
<itemfourth displayname="216" />
<itemfourth displayname="217" />
<itemfourth displayname="218" />
<itemfourth displayname="219" />
<itemfourth displayname="220" />
<itemfourth displayname="221" />
<itemfourth displayname="222" />
<itemfourth displayname="223" />
<itemfourth displayname="224" />
<itemfourth displayname="225" />
<itemfourth displayname="226" />
<itemfourth displayname="227" />
<itemfourth displayname="228" />
<itemfourth displayname="229" />
<itemfourth displayname="230" />
<itemfourth displayname="231" />
<itemfourth displayname="232" />
<itemfourth displayname="233" />
<itemfourth displayname="234" />
<itemfourth displayname="235" />
<itemfourth displayname="236" />
<itemfourth displayname="237" />
<itemfourth displayname="238" />
<itemfourth displayname="239" />
<itemfourth displayname="240" />
<itemfourth displayname="241" />
<itemfourth displayname="242" />
<itemfourth displayname="243" />
<itemfourth displayname="244" />
<itemfourth displayname="245" />
<itemfourth displayname="246" />
<itemfourth displayname="247" />
<itemfourth displayname="248" />
<itemfourth displayname="249" />
<itemfourth displayname="250" />
<itemfourth displayname="251" />
<itemfourth displayname="252" />
<itemfourth displayname="253" />
<itemfourth displayname="254" />
</column>
</model>